corecomb/__init__.py
corecomb-0.2.1.dist-info/LICENSE
corecomb-0.2.1.dist-info/METADATA
corecomb-0.2.1.dist-info/WHEEL
corecomb-0.2.1.dist-info/entry_points.txt
corecomb-0.2.1.dist-info/RECORD
