Metadata-Version: 2.1
Name: corecomb
Version: 0.2.1
Summary: 
Author: maxibor
Author-email: maxime_borry@eva.mpg.de
Requires-Python: >=3.10,<4.0
Classifier: Programming Language :: Python :: 3
Classifier: Programming Language :: Python :: 3.10
Classifier: Programming Language :: Python :: 3.11
Classifier: Programming Language :: Python :: 3.12
Requires-Dist: click (>=8.1.7,<9.0.0)
Requires-Dist: pysam (>=0.22.0,<0.23.0)
Requires-Dist: pytest (>=8.0.0,<9.0.0)
Requires-Dist: rich-click (>=1.7.3,<2.0.0)
